basicbenchmark/__init__.py
basicbenchmark/benchmark.py
basicbenchmark/decorators.py
basicbenchmark/py.typed
basicbenchmark-0.2.0.dist-info/METADATA
basicbenchmark-0.2.0.dist-info/WHEEL
basicbenchmark-0.2.0.dist-info/licenses/LICENSE
basicbenchmark-0.2.0.dist-info/RECORD
